PictureCombiner/PictureCombiner.py
PictureCombiner/__init__.py
PictureCombiner-1.0.1.dist-info/LICENSE
PictureCombiner-1.0.1.dist-info/METADATA
PictureCombiner-1.0.1.dist-info/WHEEL
PictureCombiner-1.0.1.dist-info/top_level.txt
PictureCombiner-1.0.1.dist-info/RECORD
