Metadata-Version: 2.1
Name: PictureCombiner
Version: 1.0.1
Summary: 提供图片拼接功能
Home-page: https://github.com/yangjinming1062/PictureCombiner
Author: YangJinming
Author-email: 944596544@qq.com
License: UNKNOWN
Platform: UNKNOWN
Classifier: Programming Language :: Python :: 3
Classifier: License :: OSI Approved :: MIT License
Classifier: Operating System :: OS Independent
Requires-Python: >=3.6
